sqllineage/__init__.py
sqllineage/cli.py
sqllineage/drawing.py
sqllineage/exceptions.py
sqllineage/io.py
sqllineage/runner.py
sqllineage/core/__init__.py
sqllineage/core/analyzer.py
sqllineage/core/holders.py
sqllineage/core/models.py
sqllineage/core/handlers/__init__.py
sqllineage/core/handlers/base.py
sqllineage/core/handlers/cte.py
sqllineage/core/handlers/source.py
sqllineage/core/handlers/swap_partition.py
sqllineage/core/handlers/target.py
sqllineage/data/tpcds/query01.sql
sqllineage/data/tpcds/query02.sql
sqllineage/data/tpcds/query03.sql
sqllineage/data/tpcds/query04.sql
sqllineage/data/tpcds/query05.sql
sqllineage/data/tpcds/query06.sql
sqllineage/data/tpcds/query07.sql
sqllineage/data/tpcds/query08.sql
sqllineage/data/tpcds/query09.sql
sqllineage/data/tpcds/query10.sql
sqllineage/data/tpcds/query11.sql
sqllineage/data/tpcds/query12.sql
sqllineage/data/tpcds/query13.sql
sqllineage/data/tpcds/query14.sql
sqllineage/data/tpcds/query15.sql
sqllineage/data/tpcds/query16.sql
sqllineage/data/tpcds/query17.sql
sqllineage/data/tpcds/query18.sql
sqllineage/data/tpcds/query19.sql
sqllineage/data/tpcds/query20.sql
sqllineage/data/tpcds/query21.sql
sqllineage/data/tpcds/query22.sql
sqllineage/data/tpcds/query23.sql
sqllineage/data/tpcds/query24.sql
sqllineage/data/tpcds/query25.sql
sqllineage/data/tpcds/query26.sql
sqllineage/data/tpcds/query27.sql
sqllineage/data/tpcds/query28.sql
sqllineage/data/tpcds/query29.sql
sqllineage/data/tpcds/query30.sql
sqllineage/data/tpcds/query31.sql
sqllineage/data/tpcds/query32.sql
sqllineage/data/tpcds/query33.sql
sqllineage/data/tpcds/query34.sql
sqllineage/data/tpcds/query35.sql
sqllineage/data/tpcds/query36.sql
sqllineage/data/tpcds/query37.sql
sqllineage/data/tpcds/query38.sql
sqllineage/data/tpcds/query39.sql
sqllineage/data/tpcds/query40.sql
sqllineage/data/tpcds/query41.sql
sqllineage/data/tpcds/query42.sql
sqllineage/data/tpcds/query43.sql
sqllineage/data/tpcds/query44.sql
sqllineage/data/tpcds/query45.sql
juneyaodag-1.0.1.dist-info/LICENSE
juneyaodag-1.0.1.dist-info/METADATA
juneyaodag-1.0.1.dist-info/WHEEL
juneyaodag-1.0.1.dist-info/entry_points.txt
juneyaodag-1.0.1.dist-info/top_level.txt
juneyaodag-1.0.1.dist-info/RECORD
